screen_scout/__init__.py
screen_scout/__main__.py
screen_scout/_cli.py
screen_scout/agent.py
screen_scout/main_async.py
screen_scout/templates.py
screen_scout/test_creation_util.py
screen_scout-2.0.11.dist-info/METADATA
screen_scout-2.0.11.dist-info/WHEEL
screen_scout-2.0.11.dist-info/entry_points.txt
screen_scout-2.0.11.dist-info/top_level.txt
screen_scout-2.0.11.dist-info/RECORD
