Metadata-Version: 2.1
Name: screen-scout
Version: 2.0.11
Summary: Automated UI testing tool
Author: ScreenScout Team
Author-email: team@usescreenscout.com
Classifier: Programming Language :: Python :: 3
Classifier: License :: OSI Approved :: MIT License
Classifier: Operating System :: OS Independent
Requires-Dist: nest-asyncio
